mypyq/__init__.py
mypyq/core.py
mypyq/example.py
mypyq-1.0.0.dist-info/METADATA
mypyq-1.0.0.dist-info/WHEEL
mypyq-1.0.0.dist-info/licenses/LICENCE
mypyq-1.0.0.dist-info/RECORD
