Metadata-Version: 2.4
Name: mypyq
Version: 1.0.0
Summary: A small API wrapper for garage doors using the MyQ API.
Project-URL: Homepage, https://github.com/yodaluca23/mypythonq
Project-URL: Issues, https://github.com/yodaluca23/mypythonq/issues
Author-email: yodaluca23 <mypyq@yodaluca.dev>
License-Expression: MIT
License-File: LICENCE
Classifier: Operating System :: OS Independent
Classifier: Programming Language :: Python :: 3
Requires-Python: >=3.9
Requires-Dist: requests>=2.32.5
